eazyml_augi/__init__.py
eazyml_augi/Darwin_arm64/__init__.py
eazyml_augi/Darwin_arm64/eazyml_augi/__init__.cpython-310-darwin.so
eazyml_augi/Darwin_arm64/eazyml_augi/__init__.cpython-311-darwin.so
eazyml_augi/Darwin_arm64/eazyml_augi/__init__.cpython-312-darwin.so
eazyml_augi/Darwin_arm64/eazyml_augi/__init__.cpython-38-darwin.so
eazyml_augi/Darwin_arm64/eazyml_augi/__init__.cpython-39-darwin.so
eazyml_augi/Darwin_arm64/eazyml_augi/client.cpython-310-darwin.so
eazyml_augi/Darwin_arm64/eazyml_augi/client.cpython-311-darwin.so
eazyml_augi/Darwin_arm64/eazyml_augi/client.cpython-312-darwin.so
eazyml_augi/Darwin_arm64/eazyml_augi/client.cpython-38-darwin.so
eazyml_augi/Darwin_arm64/eazyml_augi/client.cpython-39-darwin.so
eazyml_augi/Darwin_arm64/eazyml_augi/test_client.cpython-310-darwin.so
eazyml_augi/Darwin_arm64/eazyml_augi/test_client.cpython-311-darwin.so
eazyml_augi/Darwin_arm64/eazyml_augi/test_client.cpython-312-darwin.so
eazyml_augi/Darwin_arm64/eazyml_augi/test_client.cpython-38-darwin.so
eazyml_augi/Darwin_arm64/eazyml_augi/test_client.cpython-39-darwin.so
eazyml_augi/Darwin_arm64/eazyml_augi/globals/__init__.cpython-310-darwin.so
eazyml_augi/Darwin_arm64/eazyml_augi/globals/__init__.cpython-311-darwin.so
eazyml_augi/Darwin_arm64/eazyml_augi/globals/__init__.cpython-312-darwin.so
eazyml_augi/Darwin_arm64/eazyml_augi/globals/__init__.cpython-38-darwin.so
eazyml_augi/Darwin_arm64/eazyml_augi/globals/__init__.cpython-39-darwin.so
eazyml_augi/Darwin_arm64/eazyml_augi/globals/config.cpython-310-darwin.so
eazyml_augi/Darwin_arm64/eazyml_augi/globals/config.cpython-311-darwin.so
eazyml_augi/Darwin_arm64/eazyml_augi/globals/config.cpython-312-darwin.so
eazyml_augi/Darwin_arm64/eazyml_augi/globals/config.cpython-38-darwin.so
eazyml_augi/Darwin_arm64/eazyml_augi/globals/config.cpython-39-darwin.so
eazyml_augi/Darwin_arm64/eazyml_augi/globals/transparency_api.cpython-310-darwin.so
eazyml_augi/Darwin_arm64/eazyml_augi/globals/transparency_api.cpython-311-darwin.so
eazyml_augi-0.0.36.dist-info/LICENSE
eazyml_augi-0.0.36.dist-info/METADATA
eazyml_augi-0.0.36.dist-info/WHEEL
eazyml_augi-0.0.36.dist-info/top_level.txt
eazyml_augi-0.0.36.dist-info/RECORD
